{"drilldown":[{"amount":null,"num_entries":1},{"depname":"總統府","amount":954900000,"num_entries":8,"cat":"總統府主管"},{"depname":"國家安全會議","amount":204781000,"num_entries":4,"cat":"總統府主管"},{"depname":"國史館","amount":206500000,"num_entries":5,"cat":"總統府主管"},{"depname":"國史館臺灣文獻館","amount":98114000,"num_entries":4,"cat":"總統府主管"},{"depname":"中央研究院","amount":15539287000,"num_entries":10,"cat":"總統府主管"},{"depname":"行政院","amount":1241236000,"num_entries":15,"cat":"行政院主管"},{"depname":"主計總處","amount":1075964000,"num_entries":12,"cat":"行政院主管"},{"depname":"人事行政總處","amount":2481467000,"num_entries":12,"cat":"行政院主管"},{"depname":"公務人力發展中心","amount":130340000,"num_entries":3,"cat":"行政院主管"},{"depname":"地方行政研習中心","amount":130933000,"num_entries":4,"cat":"行政院主管"},{"depname":"國立故宮博物院","amount":3858478000,"num_entries":15,"cat":"行政院主管"},{"depname":"國家發展委員會","amount":1899850000,"num_entries":14,"cat":"行政院主管"},{"depname":"檔案管理局","amount":319489000,"num_entries":10,"cat":"行政院主管"},{"depname":"原住民族委員會","amount":7134275000,"num_entries":11,"cat":"行政院主管"},{"depname":"文化園區管理局","amount":132729000,"num_entries":5,"cat":"行政院主管"},{"depname":"客家委員會及所屬","amount":2707441000,"num_entries":7,"cat":"行政院主管"},{"depname":"中央選舉委員會及所屬","amount":2476623000,"num_entries":7,"cat":"行政院主管"},{"depname":"公平交易委員會","amount":342514000,"num_entries":9,"cat":"行政院主管"},{"depname":"國家通訊傳播委員會","amount":678132000,"num_entries":2,"cat":"行政院主管"},{"depname":"大陸委員會","amount":981754000,"num_entries":9,"cat":"行政院主管"},{"depname":"飛航安全調查委員會","amount":53353000,"num_entries":3,"cat":"行政院主管"},{"depname":"公共工程委員會","amount":371082000,"num_entries":5,"cat":"行政院主管"},{"depname":"立法院","amount":3551194000,"num_entries":14,"cat":"立法院主管"},{"depname":"司法院","amount":2257173000,"num_entries":12,"cat":"司法院主管"},{"depname":"最高法院","amount":518240000,"num_entries":5,"cat":"司法院主管"},{"depname":"最高行政法院","amount":178796000,"num_entries":4,"cat":"司法院主管"},{"depname":"臺北高等行政法院","amount":300017000,"num_entries":5,"cat":"司法院主管"},{"depname":"臺中高等行政法院","amount":122292000,"num_entries":4,"cat":"司法院主管"},{"depname":"高雄高等行政法院","amount":159541000,"num_entries":4,"cat":"司法院主管"},{"depname":"公務員懲戒委員會","amount":91113000,"num_entries":4,"cat":"司法院主管"},{"depname":"法官學院","amount":163117000,"num_entries":4,"cat":"司法院主管"},{"depname":"智慧財產法院","amount":204744000,"num_entries":4,"cat":"司法院主管"},{"depname":"臺灣高等法院","amount":1623938000,"num_entries":8,"cat":"司法院主管"},{"depname":"臺灣高等法院臺中分院","amount":643552000,"num_entries":5,"cat":"司法院主管"},{"depname":"臺灣高等法院臺南分院","amount":406759000,"num_entries":5,"cat":"司法院主管"},{"depname":"臺灣高等法院高雄分院","amount":492766000,"num_entries":5,"cat":"司法院主管"},{"depname":"臺灣高等法院花蓮分院","amount":150800000,"num_entries":5,"cat":"司法院主管"},{"depname":"臺灣臺北地方法院","amount":1604743000,"num_entries":8,"cat":"司法院主管"},{"depname":"臺灣士林地方法院","amount":718217000,"num_entries":7,"cat":"司法院主管"},{"depname":"臺灣新北地方法院","amount":1234658000,"num_entries":7,"cat":"司法院主管"},{"depname":"臺灣桃園地方法院","amount":1303323000,"num_entries":8,"cat":"司法院主管"},{"depname":"臺灣新竹地方法院","amount":842869000,"num_entries":8,"cat":"司法院主管"},{"depname":"臺灣苗栗地方法院","amount":310722000,"num_entries":7,"cat":"司法院主管"},{"depname":"臺灣臺中地方法院","amount":1316451000,"num_entries":7,"cat":"司法院主管"},{"depname":"臺灣南投地方法院","amount":306483000,"num_entries":6,"cat":"司法院主管"},{"depname":"臺灣彰化地方法院","amount":1033144000,"num_entries":8,"cat":"司法院主管"},{"depname":"臺灣雲林地方法院","amount":389505000,"num_entries":6,"cat":"司法院主管"},{"depname":"臺灣嘉義地方法院","amount":453811000,"num_entries":6,"cat":"司法院主管"},{"depname":"臺灣臺南地方法院","amount":974071000,"num_entries":8,"cat":"司法院主管"},{"depname":"臺灣高雄地方法院","amount":1710418000,"num_entries":7,"cat":"司法院主管"},{"depname":"臺灣屏東地方法院","amount":501572000,"num_entries":7,"cat":"司法院主管"},{"depname":"臺灣臺東地方法院","amount":220737000,"num_entries":7,"cat":"司法院主管"},{"depname":"臺灣花蓮地方法院","amount":279354000,"num_entries":7,"cat":"司法院主管"},{"depname":"臺灣宜蘭地方法院","amount":274050000,"num_entries":7,"cat":"司法院主管"},{"depname":"臺灣基隆地方法院","amount":320865000,"num_entries":7,"cat":"司法院主管"},{"depname":"臺灣澎湖地方法院","amount":115359000,"num_entries":6,"cat":"司法院主管"},{"depname":"臺灣高雄少年及家事法院","amount":261989000,"num_entries":5,"cat":"司法院主管"},{"depname":"福建高等法院金門分院","amount":33190000,"num_entries":5,"cat":"司法院主管"},{"depname":"福建金門地方法院","amount":108786000,"num_entries":8,"cat":"司法院主管"},{"depname":"福建連江地方法院","amount":25774000,"num_entries":6,"cat":"司法院主管"},{"depname":"考試院","amount":355471000,"num_entries":6,"cat":"考試院主管"},{"depname":"考選部","amount":331722000,"num_entries":6,"cat":"考試院主管"},{"depname":"銓敘部","amount":24318497000,"num_entries":8,"cat":"考試院主管"},{"depname":"公務人員保障暨培訓委員會","amount":174322000,"num_entries":5,"cat":"考試院主管"},{"depname":"國家文官學院及所屬","amount":320909000,"num_entries":5,"cat":"考試院主管"},{"depname":"公務人員退休撫卹基金監理委員會","amount":41089000,"num_entries":3,"cat":"考試院主管"},{"depname":"公務人員退休撫卹基金管理委員會","amount":883328000,"num_entries":4,"cat":"考試院主管"},{"depname":"監察院","amount":722655000,"num_entries":7,"cat":"監察院主管"},{"depname":"審計部","amount":1087733000,"num_entries":7,"cat":"監察院主管"},{"depname":"審計部臺北市審計處","amount":70043000,"num_entries":3,"cat":"監察院主管"},{"depname":"審計部新北市審計處","amount":55564000,"num_entries":4,"cat":"監察院主管"},{"depname":"審計部桃園市審計處","amount":40708000,"num_entries":3,"cat":"監察院主管"},{"depname":"審計部臺中市審計處","amount":59594000,"num_entries":3,"cat":"監察院主管"},{"depname":"審計部臺南市審計處","amount":59012000,"num_entries":3,"cat":"監察院主管"},{"depname":"審計部高雄市審計處","amount":74022000,"num_entries":4,"cat":"監察院主管"},{"depname":"內政部","amount":27384081000,"num_entries":13,"cat":"內政部主管"},{"depname":"營建署及所屬","amount":24822350000,"num_entries":17,"cat":"內政部主管"},{"depname":"警政署及所屬","amount":20177590000,"num_entries":12,"cat":"內政部主管"},{"depname":"中央警察大學","amount":1523951000,"num_entries":5,"cat":"內政部主管"},{"depname":"消防署及所屬","amount":1549652000,"num_entries":4,"cat":"內政部主管"},{"depname":"役政署","amount":5822667000,"num_entries":3,"cat":"內政部主管"},{"depname":"入出國及移民署","amount":4070647000,"num_entries":4,"cat":"內政部主管"},{"depname":"建築研究所","amount":467697000,"num_entries":3,"cat":"內政部主管"},{"depname":"空中勤務總隊","amount":2573629000,"num_entries":5,"cat":"內政部主管"},{"depname":"外交部","amount":22721160000,"num_entries":10,"cat":"外交部主管"},{"depname":"領事事務局","amount":1413698000,"num_entries":5,"cat":"外交部主管"},{"depname":"外交及國際事務學院","amount":96000000,"num_entries":3,"cat":"外交部主管"},{"depname":"國防部","amount":1479410000,"num_entries":6,"cat":"國防部主管"},{"depname":"國防部所屬","amount":317804906000,"num_entries":18,"cat":"國防部主管"},{"depname":"財政部","amount":18828159000,"num_entries":11,"cat":"財政部主管"},{"depname":"國庫署","amount":137053372000,"num_entries":7,"cat":"財政部主管"},{"depname":"賦稅署","amount":15618899000,"num_entries":5,"cat":"財政部主管"},{"depname":"臺北國稅局","amount":2405193000,"num_entries":4,"cat":"財政部主管"},{"depname":"高雄國稅局","amount":1551876000,"num_entries":4,"cat":"財政部主管"},{"depname":"北區國稅局及所屬","amount":2643005000,"num_entries":5,"cat":"財政部主管"},{"depname":"中區國稅局及所屬","amount":2135717000,"num_entries":5,"cat":"財政部主管"},{"depname":"南區國稅局及所屬","amount":1664564000,"num_entries":4,"cat":"財政部主管"},{"depname":"關務署及所屬","amount":5911595000,"num_entries":4,"cat":"財政部主管"},{"depname":"國有財產署及所屬","amount":1867523000,"num_entries":5,"cat":"財政部主管"},{"depname":"財政資訊中心","amount":1088954000,"num_entries":4,"cat":"財政部主管"},{"depname":"教育部","amount":120511050000,"num_entries":17,"cat":"教育部主管"},{"depname":"國民及學前教育署","amount":87843773000,"num_entries":5,"cat":"教育部主管"},{"depname":"體育署","amount":7849275000,"num_entries":6,"cat":"教育部主管"},{"depname":"青年發展署","amount":397112000,"num_entries":6,"cat":"教育部主管"},{"depname":"國家圖書館","amount":302449000,"num_entries":10,"cat":"教育部主管"},{"depname":"國立公共資訊圖書館","amount":161813000,"num_entries":3,"cat":"教育部主管"},{"depname":"國立教育廣播電臺","amount":185706000,"num_entries":3,"cat":"教育部主管"},{"depname":"國家教育研究院","amount":571261000,"num_entries":3,"cat":"教育部主管"},{"depname":"國立海洋科技博物館","amount":120867000,"num_entries":4,"cat":"教育部主管"},{"depname":"法務部","amount":1752300000,"num_entries":8,"cat":"法務部主管"},{"depname":"司法官學院","amount":213773000,"num_entries":3,"cat":"法務部主管"},{"depname":"法醫研究所","amount":140522000,"num_entries":5,"cat":"法務部主管"},{"depname":"廉政署","amount":421416000,"num_entries":5,"cat":"法務部主管"},{"depname":"矯正署及所屬","amount":11771515000,"num_entries":6,"cat":"法務部主管"},{"depname":"行政執行署及所屬","amount":1251445000,"num_entries":6,"cat":"法務部主管"},{"depname":"最高法院檢察署","amount":223873000,"num_entries":3,"cat":"法務部主管"},{"depname":"臺灣高等法院檢察署","amount":831100000,"num_entries":5,"cat":"法務部主管"},{"depname":"臺灣高等法院臺中分院檢察署","amount":181814000,"num_entries":3,"cat":"法務部主管"},{"depname":"臺灣高等法院臺南分院檢察署","amount":131693000,"num_entries":3,"cat":"法務部主管"},{"depname":"臺灣高等法院高雄分院檢察署","amount":166166000,"num_entries":3,"cat":"法務部主管"},{"depname":"臺灣高等法院花蓮分院檢察署","amount":54651000,"num_entries":3,"cat":"法務部主管"},{"depname":"臺灣高等法院檢察署智慧財產分署","amount":17758000,"num_entries":3,"cat":"法務部主管"},{"depname":"臺灣臺北地方法院檢察署","amount":923581000,"num_entries":5,"cat":"法務部主管"},{"depname":"臺灣士林地方法院檢察署","amount":525747000,"num_entries":4,"cat":"法務部主管"},{"depname":"臺灣新北地方法院檢察署","amount":704748000,"num_entries":4,"cat":"法務部主管"},{"depname":"臺灣桃園地方法院檢察署","amount":592285000,"num_entries":5,"cat":"法務部主管"},{"depname":"臺灣新竹地方法院檢察署","amount":287825000,"num_entries":4,"cat":"法務部主管"},{"depname":"臺灣苗栗地方法院檢察署","amount":195152000,"num_entries":3,"cat":"法務部主管"},{"depname":"臺灣臺中地方法院檢察署","amount":767980000,"num_entries":3,"cat":"法務部主管"},{"depname":"臺灣南投地方法院檢察署","amount":190322000,"num_entries":3,"cat":"法務部主管"},{"depname":"臺灣彰化地方法院檢察署","amount":313668000,"num_entries":3,"cat":"法務部主管"},{"depname":"臺灣雲林地方法院檢察署","amount":193564000,"num_entries":3,"cat":"法務部主管"},{"depname":"臺灣嘉義地方法院檢察署","amount":268241000,"num_entries":3,"cat":"法務部主管"},{"depname":"臺灣臺南地方法院檢察署","amount":478640000,"num_entries":3,"cat":"法務部主管"},{"depname":"臺灣高雄地方法院檢察署","amount":939745000,"num_entries":5,"cat":"法務部主管"},{"depname":"臺灣屏東地方法院檢察署","amount":254197000,"num_entries":4,"cat":"法務部主管"},{"depname":"臺灣臺東地方法院檢察署","amount":129748000,"num_entries":3,"cat":"法務部主管"},{"depname":"臺灣花蓮地方法院檢察署","amount":163476000,"num_entries":3,"cat":"法務部主管"},{"depname":"臺灣宜蘭地方法院檢察署","amount":158578000,"num_entries":3,"cat":"法務部主管"},{"depname":"臺灣基隆地方法院檢察署","amount":185836000,"num_entries":3,"cat":"法務部主管"},{"depname":"臺灣澎湖地方法院檢察署","amount":79232000,"num_entries":4,"cat":"法務部主管"},{"depname":"福建高等法院金門分院檢察署","amount":20734000,"num_entries":4,"cat":"法務部主管"},{"depname":"福建金門地方法院檢察署","amount":48355000,"num_entries":3,"cat":"法務部主管"},{"depname":"福建連江地方法院檢察署","amount":16431000,"num_entries":4,"cat":"法務部主管"},{"depname":"調查局","amount":5485206000,"num_entries":8,"cat":"法務部主管"},{"depname":"經濟部","amount":22038464000,"num_entries":21,"cat":"經濟部主管"},{"depname":"工業局","amount":6759304000,"num_entries":5,"cat":"經濟部主管"},{"depname":"國際貿易局及所屬","amount":2017187000,"num_entries":4,"cat":"經濟部主管"},{"depname":"標準檢驗局及所屬","amount":2309050000,"num_entries":6,"cat":"經濟部主管"},{"depname":"智慧財產局","amount":1681877000,"num_entries":4,"cat":"經濟部主管"},{"depname":"水利署及所屬","amount":16726910000,"num_entries":8,"cat":"經濟部主管"},{"depname":"中小企業處","amount":2286623000,"num_entries":4,"cat":"經濟部主管"},{"depname":"加工出口區管理處及所屬","amount":452689000,"num_entries":4,"cat":"經濟部主管"},{"depname":"中央地質調查所","amount":592180000,"num_entries":4,"cat":"經濟部主管"},{"depname":"能源局","amount":204458000,"num_entries":2,"cat":"經濟部主管"},{"depname":"交通部","amount":51233800000,"num_entries":18,"cat":"交通部主管"},{"depname":"民用航空局","amount":311258000,"num_entries":3,"cat":"交通部主管"},{"depname":"中央氣象局","amount":2015760000,"num_entries":9,"cat":"交通部主管"},{"depname":"觀光局及所屬","amount":5196585000,"num_entries":5,"cat":"交通部主管"},{"depname":"運輸研究所","amount":403822000,"num_entries":5,"cat":"交通部主管"},{"depname":"公路總局及所屬","amount":53541602000,"num_entries":5,"cat":"交通部主管"},{"depname":"勞動部","amount":114978015000,"num_entries":8,"cat":"勞動部主管"},{"depname":"勞工保險局","amount":3429665000,"num_entries":5,"cat":"勞動部主管"},{"depname":"勞動力發展署及所屬","amount":1975899000,"num_entries":14,"cat":"勞動部主管"},{"depname":"職業安全衛生署","amount":739284000,"num_entries":5,"cat":"勞動部主管"},{"depname":"勞動基金運用局","amount":182618000,"num_entries":3,"cat":"勞動部主管"},{"depname":"勞動及職業安全衛生研究所","amount":291680000,"num_entries":4,"cat":"勞動部主管"},{"depname":"蒙藏委員會","amount":125406000,"num_entries":4,"cat":"蒙藏委員會主管"},{"depname":"僑務委員會","amount":1402249000,"num_entries":11,"cat":"僑務委員會主管"},{"depname":"原子能委員會","amount":614931000,"num_entries":7,"cat":"原子能委員會主管"},{"depname":"輻射偵測中心","amount":73927000,"num_entries":5,"cat":"原子能委員會主管"},{"depname":"放射性物料管理局","amount":84259000,"num_entries":6,"cat":"原子能委員會主管"},{"depname":"核能研究所","amount":2247252000,"num_entries":8,"cat":"原子能委員會主管"},{"depname":"農業委員會","amount":99481160000,"num_entries":9,"cat":"農業委員會主管"},{"depname":"林務局","amount":6497772000,"num_entries":6,"cat":"農業委員會主管"},{"depname":"水土保持局","amount":4603450000,"num_entries":4,"cat":"農業委員會主管"},{"depname":"農業試驗所","amount":1013842000,"num_entries":5,"cat":"農業委員會主管"},{"depname":"林業試驗所","amount":609926000,"num_entries":5,"cat":"農業委員會主管"},{"depname":"水產試驗所","amount":568579000,"num_entries":4,"cat":"農業委員會主管"},{"depname":"畜產試驗所","amount":627563000,"num_entries":4,"cat":"農業委員會主管"},{"depname":"家畜衛生試驗所","amount":402549000,"num_entries":5,"cat":"農業委員會主管"},{"depname":"農業藥物毒物試驗所","amount":316456000,"num_entries":4,"cat":"農業委員會主管"},{"depname":"特有生物研究保育中心","amount":320098000,"num_entries":4,"cat":"農業委員會主管"},{"depname":"茶業改良場","amount":234064000,"num_entries":4,"cat":"農業委員會主管"},{"depname":"種苗改良繁殖場","amount":205314000,"num_entries":5,"cat":"農業委員會主管"},{"depname":"桃園區農業改良場","amount":212765000,"num_entries":4,"cat":"農業委員會主管"},{"depname":"苗栗區農業改良場","amount":131657000,"num_entries":4,"cat":"農業委員會主管"},{"depname":"臺中區農業改良場","amount":227099000,"num_entries":3,"cat":"農業委員會主管"},{"depname":"臺南區農業改良場","amount":253060000,"num_entries":4,"cat":"農業委員會主管"},{"depname":"高雄區農業改良場","amount":211666000,"num_entries":3,"cat":"農業委員會主管"},{"depname":"花蓮區農業改良場","amount":171182000,"num_entries":3,"cat":"農業委員會主管"},{"depname":"臺東區農業改良場","amount":137548000,"num_entries":3,"cat":"農業委員會主管"},{"depname":"漁業署及所屬","amount":4579168000,"num_entries":6,"cat":"農業委員會主管"},{"depname":"動植物防疫檢疫局及所屬","amount":1829540000,"num_entries":6,"cat":"農業委員會主管"},{"depname":"農業金融局","amount":306942000,"num_entries":5,"cat":"農業委員會主管"},{"depname":"農糧署及所屬","amount":1745579000,"num_entries":5,"cat":"農業委員會主管"},{"depname":"衛生福利部","amount":136714637000,"num_entries":20,"cat":"衛生福利部主管"},{"depname":"疾病管制署","amount":5498748000,"num_entries":5,"cat":"衛生福利部主管"},{"depname":"食品藥物管理署","amount":2413940000,"num_entries":5,"cat":"衛生福利部主管"},{"depname":"中央健康保險署","amount":5558535000,"num_entries":5,"cat":"衛生福利部主管"},{"depname":"國民健康署","amount":2908362000,"num_entries":4,"cat":"衛生福利部主管"},{"depname":"社會及家庭署","amount":22533700000,"num_entries":6,"cat":"衛生福利部主管"},{"depname":"國家中醫藥研究所","amount":152062000,"num_entries":4,"cat":"衛生福利部主管"},{"depname":"環境保護署","amount":4060065000,"num_entries":13,"cat":"環境保護署主管"},{"depname":"環境檢驗所","amount":279428000,"num_entries":8,"cat":"環境保護署主管"},{"depname":"環境保護人員訓練所","amount":71860000,"num_entries":4,"cat":"環境保護署主管"},{"depname":"文化部","amount":11649439000,"num_entries":21,"cat":"文化部主管"},{"depname":"文化資產局","amount":981420000,"num_entries":3,"cat":"文化部主管"},{"depname":"影視及流行音樂產業局","amount":1631828000,"num_entries":5,"cat":"文化部主管"},{"depname":"國立傳統藝術中心","amount":913752000,"num_entries":5,"cat":"文化部主管"},{"depname":"國立臺灣美術館及所屬","amount":618726000,"num_entries":7,"cat":"文化部主管"},{"depname":"國立臺灣工藝研究發展中心","amount":275096000,"num_entries":3,"cat":"文化部主管"},{"depname":"國立臺灣博物館","amount":359907000,"num_entries":4,"cat":"文化部主管"},{"depname":"國立臺灣史前文化博物館","amount":582175000,"num_entries":3,"cat":"文化部主管"},{"depname":"海岸巡防署","amount":2433409000,"num_entries":3,"cat":"海岸巡防署主管"},{"depname":"海洋巡防總局","amount":6855536000,"num_entries":4,"cat":"海岸巡防署主管"},{"depname":"海岸巡防總局及所屬","amount":6065133000,"num_entries":5,"cat":"海岸巡防署主管"},{"depname":"科技部","amount":46000348000,"num_entries":6,"cat":"科技部主管"},{"depname":"新竹科學工業園區管理局及所屬","amount":902248000,"num_entries":12,"cat":"科技部主管"},{"depname":"中部科學工業園區管理局及所屬","amount":1497462000,"num_entries":11,"cat":"科技部主管"},{"depname":"南部科學工業園區管理局及所屬","amount":1169643000,"num_entries":11,"cat":"科技部主管"},{"depname":"金融監督管理委員會","amount":222345000,"num_entries":5,"cat":"金融監督管理委員會主管"},{"depname":"銀行局","amount":343525000,"num_entries":3,"cat":"金融監督管理委員會主管"},{"depname":"證券期貨局","amount":336926000,"num_entries":4,"cat":"金融監督管理委員會主管"},{"depname":"保險局","amount":145596000,"num_entries":3,"cat":"金融監督管理委員會主管"},{"depname":"檢查局","amount":413214000,"num_entries":4,"cat":"金融監督管理委員會主管"},{"depname":"國軍退除役官兵輔導委員會","amount":125965387000,"num_entries":13,"cat":"國軍退除役官兵輔導委員會主管"},{"depname":"臺灣省政府","amount":155661000,"num_entries":4,"cat":"省市地方政府"},{"depname":"臺灣省諮議會","amount":71256000,"num_entries":11,"cat":"省市地方政府"},{"depname":"補助直轄市及縣市政府","amount":174151928000,"num_entries":10,"cat":"省市地方政府"},{"depname":"福建省政府","amount":102173000,"num_entries":6,"cat":"省市地方政府"},{"depname":"災害準備金","amount":2000000000,"num_entries":1,"cat":"災害準備金"},{"depname":"第二預備金","amount":7500000000,"num_entries":1,"cat":"第二預備金"}],"summary":{"pagesize":1000000,"cached":true,"num_entries":1392,"page":1,"currency":{"amount":"TWD"},"amount":null,"cache_key":"8311c0ab057432fb04ac54847f5fc214e24c69cd","pages":1}}