[{"year":2016,"code":"32020070101","amount":63953000,"last_amount":63670000,"name":"行政管理","topname":"臺中市政府主管","depname":"臺中市政府研究發展考核委員會","depcat":"一般行政","category":"一般行政","cat":"臺中市政府主管","ref":"2.6.1.1","comment":"一、本科目包括行政管理二、本年度預算數包括:\n　　人事費57,145千元\n　　業務費6,724千元\n　　獎補助費84千元三、本年度預算數與上年度比較：\n　　增加 283千元\n　　增列 人事費2千元\n　　增列 業務費281千元"},{"year":2016,"code":"32020071401","amount":7513000,"last_amount":6414000,"name":"研究發展","topname":"臺中市政府主管","depname":"臺中市政府研究發展考核委員會","depcat":"施政計畫綜合業務","category":"施政計畫綜合業務","cat":"臺中市政府主管","ref":"2.6.2.1","comment":"一、本科目包括研究發展二、本年度預算數包括:\n　　人事費84千元\n　　業務費6,829千元\n　　獎補助費600千元三、本年度預算數與上年度比較：\n　　增加 1,099千元\n　　增列 業務費1,099千元"},{"year":2016,"code":"32020071402","amount":3319000,"last_amount":3319000,"name":"綜合規劃","topname":"臺中市政府主管","depname":"臺中市政府研究發展考核委員會","depcat":"施政計畫綜合業務","category":"施政計畫綜合業務","cat":"臺中市政府主管","ref":"2.6.2.2","comment":"一、本科目包括綜合規劃二、本年度預算數包括:\n　　人事費1,577千元\n　　業務費1,742千元三、本年度預算數與上年度比較：\n　　增列 人事費1千元\n　　減列 業務費1千元"},{"year":2016,"code":"32020071403","amount":4506000,"last_amount":3356000,"name":"管制考核","topname":"臺中市政府主管","depname":"臺中市政府研究發展考核委員會","depcat":"施政計畫綜合業務","category":"施政計畫綜合業務","cat":"臺中市政府主管","ref":"2.6.2.3","comment":"一、本科目包括管制考核二、本年度預算數包括:\n　　人事費108千元\n　　業務費4,398千元三、本年度預算數與上年度比較：\n　　增加 1,150千元\n　　增列 業務費1,150千元"},{"year":2016,"code":"32020071404","amount":65088000,"last_amount":54345000,"name":"為民服務","topname":"臺中市政府主管","depname":"臺中市政府研究發展考核委員會","depcat":"施政計畫綜合業務","category":"施政計畫綜合業務","cat":"臺中市政府主管","ref":"2.6.2.4","comment":"一、本科目包括為民服務二、本年度預算數包括:\n　　人事費35,027千元\n　　業務費27,101千元\n　　獎補助費2,960千元三、本年度預算數與上年度比較：\n　　增加 10,743千元\n　　增列 人事費33,222千元\n　　減列 業務費25,439千元\n　　增列 獎補助費2,960千元"},{"year":2016,"code":"32020077901","amount":500000,"last_amount":500000,"name":"第一預備金","topname":"臺中市政府主管","depname":"臺中市政府研究發展考核委員會","depcat":"第一預備金","category":"第一預備金","cat":"臺中市政府主管","ref":"2.6.3.1","comment":"一、本科目包括第一預備金二、本年度預算數包括:\n　　預備金500千元"},{"year":2016,"code":"32020079001","amount":2120000,"last_amount":700000,"name":"一般建築及設備","topname":"臺中市政府主管","depname":"臺中市政府研究發展考核委員會","depcat":"一般建築及設備","category":"一般建築及設備","cat":"臺中市政府主管","ref":"2.6.4.1","comment":"一、本科目包括一般建築及設備二、本年度預算數包括:\n　　設備及投資2,120千元三、本年度預算數與上年度比較：\n　　增加 1,420千元\n　　增列 設備及投資1,420千元"}]